pipelined_cpu.v
module pipelined_cpu(input clk, input reset);

    // Program Counter
    reg [7:0] PC;

    // Memories
    reg [15:0] instr_mem [0:15];  // 16 instructions max
    reg [7:0] data_mem [0:255];   // 256-byte data memory
    reg [7:0] regfile [0:7];      // 8 general-purpose registers R0-R7

    // Pipeline registers
    reg [15:0] IF_ID_instr;

    reg [2:0] ID_EX_op;
    reg [2:0] ID_EX_rd;
    reg [7:0] ID_EX_val1, ID_EX_val2;
    reg [7:0] ID_EX_imm;

    reg [2:0] EX_WB_rd;
    reg [7:0] EX_WB_result;
    reg       EX_WB_write;

    // === Stage 1: Instruction Fetch ===
    always @(posedge clk or posedge reset) begin
        if (reset)
            PC <= 0;
        else
            PC <= PC + 1;

        IF_ID_instr <= instr_mem[PC];
    end

    // === Stage 2: Instruction Decode ===
    wire [2:0] opcode = IF_ID_instr[15:13];
    wire [2:0] rd     = IF_ID_instr[12:10];
    wire [2:0] rs1    = IF_ID_instr[9:7];
    wire [2:0] rs2    = IF_ID_instr[6:4];
    wire [7:0] imm    = IF_ID_instr[7:0]; // for LOAD

    always @(posedge clk) begin
        ID_EX_op   <= opcode;
        ID_EX_rd   <= rd;
        ID_EX_val1 <= regfile[rs1];
        ID_EX_val2 <= regfile[rs2];
        ID_EX_imm  <= imm;
    end

    // === Stage 3: Execute ===
    reg [7:0] alu_result;
    reg       write_enable;

    always @(*) begin
        case (ID_EX_op)
            3'b000: begin // ADD
                alu_result = ID_EX_val1 + ID_EX_val2;
                write_enable = 1;
            end
            3'b001: begin // SUB
                alu_result = ID_EX_val1 - ID_EX_val2;
                write_enable = 1;
            end
            3'b010: begin // LOAD
                alu_result = data_mem[ID_EX_imm];
                write_enable = 1;
            end
            default: begin
                alu_result = 8'd0;
                write_enable = 0;
            end
        endcase
    end

    always @(posedge clk) begin
        EX_WB_result <= alu_result;
        EX_WB_rd     <= ID_EX_rd;
        EX_WB_write  <= write_enable;
    end

    // === Stage 4: Write Back ===
    always @(posedge clk) begin
        if (EX_WB_write)
            regfile[EX_WB_rd] <= EX_WB_result;
    end

endmodule

pipelined_cpu_tb.v
`timescale 1ns/1ps

module pipelined_cpu_tb;

    reg clk;
    reg reset;

    // Instantiate the processor
    pipelined_cpu cpu (
        .clk(clk),
        .reset(reset)
    );

    // Clock generation: 10ns period
    always #5 clk = ~clk;

    initial begin
        $display("Starting simulation...");
        $dumpfile("pipeline_wave.vcd");
        $dumpvars(0, pipelined_cpu_tb);

        clk = 0;
        reset = 1;

        // Hold reset briefly
        #10 reset = 0;

        // =======================
        // Instruction Memory
        // =======================
        cpu.instr_mem[0] = 16'b000_001_010_011_0000; // ADD R1 = R2 + R3
        cpu.instr_mem[1] = 16'b001_100_001_010_0000; // SUB R4 = R1 - R2
        cpu.instr_mem[2] = 16'b010_101_000_000_1100; // LOAD R5 = MEM[12]

        // =======================
        // Register File Init
        // =======================
        cpu.regfile[2] = 8'd10;  // R2 = 10
        cpu.regfile[3] = 8'd20;  // R3 = 20

        // =======================
        // Data Memory Init
        // =======================
        cpu.data_mem[12] = 8'hF0;  // MEM[12] = 240

        // Wait long enough for all instructions to execute
        #200;

        // =======================
        // Dump Register File
        // =======================
        $display("\n=== Final Register File ===");
        $display("R0 = %d", cpu.regfile[0]);
        $display("R1 = %d", cpu.regfile[1]);
        $display("R2 = %d", cpu.regfile[2]);
        $display("R3 = %d", cpu.regfile[3]);
        $display("R4 = %d", cpu.regfile[4]);
        $display("R5 = %d", cpu.regfile[5]);
        $display("R6 = %d", cpu.regfile[6]);
        $display("R7 = %d", cpu.regfile[7]);

        $finish;
    end

endmodule

pipeline_wave.vcd
$date
	Wed Jul 09 12:05:46 2025
$end
$version
	Icarus Verilog
$end
$timescale
	1ps
$end
$scope module pipelined_cpu_tb $end
$var reg 1 ! clk $end
$var reg 1 " reset $end
$scope module cpu $end
$var wire 1 ! clk $end
$var wire 1 " reset $end
$var wire 3 # rs2 [2:0] $end
$var wire 3 $ rs1 [2:0] $end
$var wire 3 % rd [2:0] $end
$var wire 3 & opcode [2:0] $end
$var wire 8 ' imm [7:0] $end
$var reg 3 ( EX_WB_rd [2:0] $end
$var reg 8 ) EX_WB_result [7:0] $end
$var reg 1 * EX_WB_write $end
$var reg 8 + ID_EX_imm [7:0] $end
$var reg 3 , ID_EX_op [2:0] $end
$var reg 3 - ID_EX_rd [2:0] $end
$var reg 8 . ID_EX_val1 [7:0] $end
$var reg 8 / ID_EX_val2 [7:0] $end
$var reg 16 0 IF_ID_instr [15:0] $end
$var reg 8 1 PC [7:0] $end
$var reg 8 2 alu_result [7:0] $end
$var reg 1 3 write_enable $end
$upscope $end
$upscope $end
$enddefinitions $end
#0
$dumpvars
x3
bx 2
b0 1
bx 0
bx /
bx .
bx -
bx ,
bx +
x*
bx )
bx (
bx '
bx &
bx %
bx $
bx #
1"
0!
$end
#5000
1!
#10000
03
b0 2
0!
0"
#15000
b0 &
b1 %
b10 $
b11 #
b110000 '
0*
b0 )
b10100110000 0
b1 1
1!
#20000
0!
#25000
13
b11110 2
b1 &
b100 %
b1 $
b10 #
b10100000 '
b110000 +
b10100 /
b1010 .
b1 -
b0 ,
b11000010100000 0
b10 1
1!
#30000
0!
#35000
bx 2
b10 &
b101 %
b0 $
b0 #
b1100 '
1*
b1 (
b11110 )
b10100000 +
b1010 /
bx .
b100 -
b1 ,
b101010000001100 0
b11 1
1!
#40000
0!
#45000
b11110000 2
bx &
bx %
bx $
bx #
bx '
b1100 +
bx /
b101 -
b10 ,
b100 (
bx )
bx 0
b100 1
1!
#50000
0!
#55000
03
b0 2
b101 (
b11110000 )
bx +
bx -
bx ,
b101 1
1!
#60000
0!
#65000
0*
bx (
b0 )
b110 1
1!
#70000
0!
#75000
b111 1
1!
#80000
0!
#85000
b1000 1
1!
#90000
0!
#95000
b1001 1
1!
#100000
0!
#105000
b1010 1
1!
#110000
0!
#115000
b1011 1
1!
#120000
0!
#125000
b1100 1
1!
#130000
0!
#135000
b1101 1
1!
#140000
0!
#145000
b1110 1
1!
#150000
0!
#155000
b1111 1
1!
#160000
0!
#165000
b10000 1
1!
#170000
0!
#175000
b10001 1
1!
#180000
0!
#185000
b10010 1
1!
#190000
0!
#195000
b10011 1
1!
#200000
0!
#205000
b10100 1
1!
