pipeline_processor.v
module pipeline_processor(input clk, input reset);

  // Instruction format: opcode[15:12] rs[11:8] rt[7:4] rd[3:0]
  reg [15:0] instruction_memory[0:15];
  reg [7:0] registers[0:15];
  reg [7:0] data_memory[0:255];

  // Pipeline registers
  reg [15:0] IF_ID;
  reg [15:0] ID_EX;
  reg [15:0] EX_WB;
  reg [7:0] EX_result;
  reg [3:0] dest_reg;

  integer pc;

  wire [3:0] opcode, rs, rt, rd;
  assign opcode = IF_ID[15:12];
  assign rs     = IF_ID[11:8];
  assign rt     = IF_ID[7:4];
  assign rd     = IF_ID[3:0];

  always @(posedge clk or posedge reset) begin
    if (reset) begin
      pc <= 0;
      IF_ID <= 0;
      ID_EX <= 0;
      EX_WB <= 0;
      EX_result <= 0;
    end else begin
      // IF Stage
      IF_ID <= instruction_memory[pc];
      pc <= pc + 1;

      // ID Stage
      ID_EX <= IF_ID;

      // EX Stage
      case (ID_EX[15:12])
        4'b0001: EX_result <= registers[ID_EX[11:8]] + registers[ID_EX[7:4]]; // ADD
        4'b0010: EX_result <= registers[ID_EX[11:8]] - registers[ID_EX[7:4]]; // SUB
        4'b0011: EX_result <= data_memory[registers[ID_EX[11:8]]];            // LOAD
        default: EX_result <= 0;
      endcase
      dest_reg <= ID_EX[3:0];
      EX_WB <= ID_EX;

      // WB Stage
      if (EX_WB[15:12] != 4'b0000) begin
        registers[dest_reg] <= EX_result;
      end
    end
  end

endmodule

testbench.v
`timescale 1ns/1ps
module testbench;

  reg clk = 0;
  reg reset = 1;

  // Instantiate the design
  pipeline_processor uut(.clk(clk), .reset(reset));

  // Generate clock
  always #5 clk = ~clk;

  initial begin
    // Dump to GTKWave
    $dumpfile("wave.vcd");
    $dumpvars(0, testbench);

    // Initialize register and memory
    uut.registers[1] = 10;  // R1 = 10
    uut.registers[2] = 5;   // R2 = 5
    uut.data_memory[10] = 20; // Mem[10] = 20

    // Load instructions
    uut.instruction_memory[0] = 16'b0001_0001_0010_0100; // ADD R1 + R2 -> R4
    uut.instruction_memory[1] = 16'b0010_0001_0010_0101; // SUB R1 - R2 -> R5
    uut.instruction_memory[2] = 16'b0011_0001_0000_0110; // LOAD [R1] -> R6

    #10 reset = 0;  // Release reset

    #100;

    $display("R4 = %d", uut.registers[4]);
    $display("R5 = %d", uut.registers[5]);
    $display("R6 = %d", uut.registers[6]);

    $finish;
  end
endmodule

wave.vcd
$date
	Wed Jul 09 14:20:37 2025
$end
$version
	Icarus Verilog
$end
$timescale
	1ps
$end
$scope module testbench $end
$var reg 1 ! clk $end
$var reg 1 " reset $end
$scope module uut $end
$var wire 1 ! clk $end
$var wire 1 " reset $end
$var wire 4 # rt [3:0] $end
$var wire 4 $ rs [3:0] $end
$var wire 4 % rd [3:0] $end
$var wire 4 & opcode [3:0] $end
$var reg 16 ' EX_WB [15:0] $end
$var reg 8 ( EX_result [7:0] $end
$var reg 16 ) ID_EX [15:0] $end
$var reg 16 * IF_ID [15:0] $end
$var reg 4 + dest_reg [3:0] $end
$var integer 32 , pc [31:0] $end
$upscope $end
$upscope $end
$enddefinitions $end
#0
$dumpvars
b0 ,
bx +
b0 *
b0 )
b0 (
b0 '
b0 &
b0 %
b0 $
b0 #
1"
0!
$end
#5000
1!
#10000
0!
0"
#15000
b1 &
b1 $
b10 #
b100 %
b0 +
b1 ,
b1000100100100 *
1!
#20000
0!
#25000
b10 &
b101 %
b1000100100100 )
b10 ,
b10000100100101 *
1!
#30000
0!
#35000
b11 &
b0 #
b110 %
b1000100100100 '
b100 +
b1111 (
b10000100100101 )
b11 ,
b11000100000110 *
1!
#40000
0!
#45000
bx &
bx $
bx #
bx %
b10000100100101 '
b101 +
b101 (
b11000100000110 )
b100 ,
bx *
1!
#50000
0!
#55000
b11000100000110 '
b110 +
b10100 (
bx )
b101 ,
1!
#60000
0!
#65000
bx '
bx +
b0 (
b110 ,
1!
#70000
0!
#75000
b111 ,
1!
#80000
0!
#85000
b1000 ,
1!
#90000
0!
#95000
b1001 ,
1!
#100000
0!
#105000
b1010 ,
1!
